sangria/__init__.py
sangria/sample.py
sangria/version.py
sangria-0.0.0.dist-info/LICENSE
sangria-0.0.0.dist-info/METADATA
sangria-0.0.0.dist-info/WHEEL
sangria-0.0.0.dist-info/top_level.txt
sangria-0.0.0.dist-info/RECORD
