Metadata-Version: 2.1
Name: sangria
Version: 0.0.0
Summary: Coming Soon
Home-page: UNKNOWN
Author: Abhilash Kishore
Author-email: abhilash1in@gmail.com
License: MIT
Project-URL: GitHub, https://github.com/abhilash1in/sangria
Platform: UNKNOWN
Classifier: License :: OSI Approved :: MIT License
Classifier: Programming Language :: Python :: 3
Requires-Python: >=3.7
License-File: LICENSE
Provides-Extra: dev
Requires-Dist: flake8 ; extra == 'dev'
Requires-Dist: black ; extra == 'dev'
